cavemanstatistics/__init__.py
cavemanstatistics/code.py
cavemanstatistics-0.5.dist-info/METADATA
cavemanstatistics-0.5.dist-info/RECORD
cavemanstatistics-0.5.dist-info/WHEEL
cavemanstatistics-0.5.dist-info/top_level.txt
