Metadata-Version: 2.1
Name: cavemanstatistics
Version: 0.5
Summary: Exhaustive-Search for best R^2 in Linear Regression Models
Home-page: https://github.com/kgeoffrey/cavemanstats
Author: Geoffrey Kasenbacher
Author-email: gkasenbacher@gmail.com
License: UNKNOWN
Platform: UNKNOWN
Classifier: Programming Language :: Python :: 3
Classifier: License :: OSI Approved :: MIT License
Classifier: Operating System :: OS Independent
Requires-Dist: numpy
Requires-Dist: pandas
Requires-Dist: scikit-learn
Requires-Dist: tabulate
Requires-Dist: scipy
